<?xml version="1.0" encoding="UTF-8"?>
<!DOCTYPE plist PUBLIC "-//Apple//DTD PLIST 1.0//EN" "http://www.apple.com/DTDs/PropertyList-1.0.dtd">
<plist version="1.0">
<dict>
	<key>Images</key>
	<array>
		<dict>
			<key>ImageIndex</key>
			<integer>0</integer>
			<key>NumberOfROIs</key>
			<integer>84</integer>
			<key>ROIs</key>
			<array>
				<dict>
					<key>Area</key>
					<real>0.0</real>
					<key>Center</key>
					<string>(0.000000, 0.000000, 0.000000)</string>
					<key>Dev</key>
					<real>0.0</real>
					<key>IndexInImage</key>
					<integer>0</integer>
					<key>Max</key>
					<real>0.0</real>
					<key>Mean</key>
					<real>0.0</real>
					<key>Min</key>
					<real>0.0</real>
					<key>Name</key>
					<string>Calcification</string>
					<key>NumberOfPoints</key>
					<integer>1</integer>
					<key>Point_mm</key>
					<array>
						<string>(0.000000, 0.000000, 0.000000)</string>
					</array>
					<key>Point_px</key>
					<array>
						<string>(1989.010010, 1967.660034)</string>
					</array>
					<key>Total</key>
					<real>0.0</real>
					<key>Type</key>
					<integer>19</integer>
				</dict>
				<dict>
					<key>Area</key>
					<real>0.0</real>
					<key>Center</key>
					<string>(0.000000, 0.000000, 0.000000)</string>
					<key>Dev</key>
					<real>0.0</real>
					<key>IndexInImage</key>
					<integer>1</integer>
					<key>Max</key>
					<real>0.0</real>
					<key>Mean</key>
					<real>0.0</real>
					<key>Min</key>
					<real>0.0</real>
					<key>Name</key>
					<string>Calcification</string>
					<key>NumberOfPoints</key>
					<integer>1</integer>
					<key>Point_mm</key>
					<array>
						<string>(0.000000, 0.000000, 0.000000)</string>
					</array>
					<key>Point_px</key>
					<array>
						<string>(1945.010010, 1983.589966)</string>
					</array>
					<key>Total</key>
					<real>0.0</real>
					<key>Type</key>
					<integer>19</integer>
				</dict>
				<dict>
					<key>Area</key>
					<real>0.0</real>
					<key>Center</key>
					<string>(0.000000, 0.000000, 0.000000)</string>
					<key>Dev</key>
					<real>0.0</real>
					<key>IndexInImage</key>
					<integer>2</integer>
					<key>Max</key>
					<real>0.0</real>
					<key>Mean</key>
					<real>0.0</real>
					<key>Min</key>
					<real>0.0</real>
					<key>Name</key>
					<string>Calcification</string>
					<key>NumberOfPoints</key>
					<integer>1</integer>
					<key>Point_mm</key>
					<array>
						<string>(0.000000, 0.000000, 0.000000)</string>
					</array>
					<key>Point_px</key>
					<array>
						<string>(1925.290039, 1983.589966)</string>
					</array>
					<key>Total</key>
					<real>0.0</real>
					<key>Type</key>
					<integer>19</integer>
				</dict>
				<dict>
					<key>Area</key>
					<real>0.0</real>
					<key>Center</key>
					<string>(0.000000, 0.000000, 0.000000)</string>
					<key>Dev</key>
					<real>0.0</real>
					<key>IndexInImage</key>
					<integer>3</integer>
					<key>Max</key>
					<real>0.0</real>
					<key>Mean</key>
					<real>0.0</real>
					<key>Min</key>
					<real>0.0</real>
					<key>Name</key>
					<string>Calcification</string>
					<key>NumberOfPoints</key>
					<integer>1</integer>
					<key>Point_mm</key>
					<array>
						<string>(0.000000, 0.000000, 0.000000)</string>
					</array>
					<key>Point_px</key>
					<array>
						<string>(1939.699951, 1962.349976)</string>
					</array>
					<key>Total</key>
					<real>0.0</real>
					<key>Type</key>
					<integer>19</integer>
				</dict>
				<dict>
					<key>Area</key>
					<real>0.0</real>
					<key>Center</key>
					<string>(0.000000, 0.000000, 0.000000)</string>
					<key>Dev</key>
					<real>0.0</real>
					<key>IndexInImage</key>
					<integer>4</integer>
					<key>Max</key>
					<real>0.0</real>
					<key>Mean</key>
					<real>0.0</real>
					<key>Min</key>
					<real>0.0</real>
					<key>Name</key>
					<string>Calcification</string>
					<key>NumberOfPoints</key>
					<integer>1</integer>
					<key>Point_mm</key>
					<array>
						<string>(0.000000, 0.000000, 0.000000)</string>
					</array>
					<key>Point_px</key>
					<array>
						<string>(1885.079956, 1979.040039)</string>
					</array>
					<key>Total</key>
					<real>0.0</real>
					<key>Type</key>
					<integer>19</integer>
				</dict>
				<dict>
					<key>Area</key>
					<real>0.0</real>
					<key>Center</key>
					<string>(0.000000, 0.000000, 0.000000)</string>
					<key>Dev</key>
					<real>0.0</real>
					<key>IndexInImage</key>
					<integer>5</integer>
					<key>Max</key>
					<real>0.0</real>
					<key>Mean</key>
					<real>0.0</real>
					<key>Min</key>
					<real>0.0</real>
					<key>Name</key>
					<string>Calcification</string>
					<key>NumberOfPoints</key>
					<integer>1</integer>
					<key>Point_mm</key>
					<array>
						<string>(0.000000, 0.000000, 0.000000)</string>
					</array>
					<key>Point_px</key>
					<array>
						<string>(1836.030029, 2219.989990)</string>
					</array>
					<key>Total</key>
					<real>0.0</real>
					<key>Type</key>
					<integer>19</integer>
				</dict>
				<dict>
					<key>Area</key>
					<real>0.0</real>
					<key>Center</key>
					<string>(0.000000, 0.000000, 0.000000)</string>
					<key>Dev</key>
					<real>0.0</real>
					<key>IndexInImage</key>
					<integer>6</integer>
					<key>Max</key>
					<real>0.0</real>
					<key>Mean</key>
					<real>0.0</real>
					<key>Min</key>
					<real>0.0</real>
					<key>Name</key>
					<string>Calcification</string>
					<key>NumberOfPoints</key>
					<integer>1</integer>
					<key>Point_mm</key>
					<array>
						<string>(0.000000, 0.000000, 0.000000)</string>
					</array>
					<key>Point_px</key>
					<array>
						<string>(1662.199951, 2041.290039)</string>
					</array>
					<key>Total</key>
					<real>0.0</real>
					<key>Type</key>
					<integer>19</integer>
				</dict>
				<dict>
					<key>Area</key>
					<real>0.0</real>
					<key>Center</key>
					<string>(0.000000, 0.000000, 0.000000)</string>
					<key>Dev</key>
					<real>0.0</real>
					<key>IndexInImage</key>
					<integer>7</integer>
					<key>Max</key>
					<real>0.0</real>
					<key>Mean</key>
					<real>0.0</real>
					<key>Min</key>
					<real>0.0</real>
					<key>Name</key>
					<string>Calcification</string>
					<key>NumberOfPoints</key>
					<integer>1</integer>
					<key>Point_mm</key>
					<array>
						<string>(0.000000, 0.000000, 0.000000)</string>
					</array>
					<key>Point_px</key>
					<array>
						<string>(1763.930054, 2167.360107)</string>
					</array>
					<key>Total</key>
					<real>0.0</real>
					<key>Type</key>
					<integer>19</integer>
				</dict>
				<dict>
					<key>Area</key>
					<real>0.0</real>
					<key>Center</key>
					<string>(0.000000, 0.000000, 0.000000)</string>
					<key>Dev</key>
					<real>0.0</real>
					<key>IndexInImage</key>
					<integer>8</integer>
					<key>Max</key>
					<real>0.0</real>
					<key>Mean</key>
					<real>0.0</real>
					<key>Min</key>
					<real>0.0</real>
					<key>Name</key>
					<string>Calcification</string>
					<key>NumberOfPoints</key>
					<integer>1</integer>
					<key>Point_mm</key>
					<array>
						<string>(0.000000, 0.000000, 0.000000)</string>
					</array>
					<key>Point_px</key>
					<array>
						<string>(1847.089966, 2093.489990)</string>
					</array>
					<key>Total</key>
					<real>0.0</real>
					<key>Type</key>
					<integer>19</integer>
				</dict>
				<dict>
					<key>Area</key>
					<real>0.0</real>
					<key>Center</key>
					<string>(0.000000, 0.000000, 0.000000)</string>
					<key>Dev</key>
					<real>0.0</real>
					<key>IndexInImage</key>
					<integer>9</integer>
					<key>Max</key>
					<real>0.0</real>
					<key>Mean</key>
					<real>0.0</real>
					<key>Min</key>
					<real>0.0</real>
					<key>Name</key>
					<string>Calcification</string>
					<key>NumberOfPoints</key>
					<integer>1</integer>
					<key>Point_mm</key>
					<array>
						<string>(0.000000, 0.000000, 0.000000)</string>
					</array>
					<key>Point_px</key>
					<array>
						<string>(1846.650024, 2085.530029)</string>
					</array>
					<key>Total</key>
					<real>0.0</real>
					<key>Type</key>
					<integer>19</integer>
				</dict>
				<dict>
					<key>Area</key>
					<real>0.0</real>
					<key>Center</key>
					<string>(0.000000, 0.000000, 0.000000)</string>
					<key>Dev</key>
					<real>0.0</real>
					<key>IndexInImage</key>
					<integer>10</integer>
					<key>Max</key>
					<real>0.0</real>
					<key>Mean</key>
					<real>0.0</real>
					<key>Min</key>
					<real>0.0</real>
					<key>Name</key>
					<string>Calcification</string>
					<key>NumberOfPoints</key>
					<integer>1</integer>
					<key>Point_mm</key>
					<array>
						<string>(0.000000, 0.000000, 0.000000)</string>
					</array>
					<key>Point_px</key>
					<array>
						<string>(1816.130005, 2114.280029)</string>
					</array>
					<key>Total</key>
					<real>0.0</real>
					<key>Type</key>
					<integer>19</integer>
				</dict>
				<dict>
					<key>Area</key>
					<real>0.0</real>
					<key>Center</key>
					<string>(0.000000, 0.000000, 0.000000)</string>
					<key>Dev</key>
					<real>0.0</real>
					<key>IndexInImage</key>
					<integer>11</integer>
					<key>Max</key>
					<real>0.0</real>
					<key>Mean</key>
					<real>0.0</real>
					<key>Min</key>
					<real>0.0</real>
					<key>Name</key>
					<string>Calcification</string>
					<key>NumberOfPoints</key>
					<integer>1</integer>
					<key>Point_mm</key>
					<array>
						<string>(0.000000, 0.000000, 0.000000)</string>
					</array>
					<key>Point_px</key>
					<array>
						<string>(1819.670044, 2089.949951)</string>
					</array>
					<key>Total</key>
					<real>0.0</real>
					<key>Type</key>
					<integer>19</integer>
				</dict>
				<dict>
					<key>Area</key>
					<real>0.0</real>
					<key>Center</key>
					<string>(0.000000, 0.000000, 0.000000)</string>
					<key>Dev</key>
					<real>0.0</real>
					<key>IndexInImage</key>
					<integer>12</integer>
					<key>Max</key>
					<real>0.0</real>
					<key>Mean</key>
					<real>0.0</real>
					<key>Min</key>
					<real>0.0</real>
					<key>Name</key>
					<string>Calcification</string>
					<key>NumberOfPoints</key>
					<integer>1</integer>
					<key>Point_mm</key>
					<array>
						<string>(0.000000, 0.000000, 0.000000)</string>
					</array>
					<key>Point_px</key>
					<array>
						<string>(1971.209961, 2193.419922)</string>
					</array>
					<key>Total</key>
					<real>0.0</real>
					<key>Type</key>
					<integer>19</integer>
				</dict>
				<dict>
					<key>Area</key>
					<real>0.0</real>
					<key>Center</key>
					<string>(0.000000, 0.000000, 0.000000)</string>
					<key>Dev</key>
					<real>0.0</real>
					<key>IndexInImage</key>
					<integer>13</integer>
					<key>Max</key>
					<real>0.0</real>
					<key>Mean</key>
					<real>0.0</real>
					<key>Min</key>
					<real>0.0</real>
					<key>Name</key>
					<string>Calcification</string>
					<key>NumberOfPoints</key>
					<integer>1</integer>
					<key>Point_mm</key>
					<array>
						<string>(0.000000, 0.000000, 0.000000)</string>
					</array>
					<key>Point_px</key>
					<array>
						<string>(1972.160034, 2178.610107)</string>
					</array>
					<key>Total</key>
					<real>0.0</real>
					<key>Type</key>
					<integer>19</integer>
				</dict>
				<dict>
					<key>Area</key>
					<real>0.0</real>
					<key>Center</key>
					<string>(0.000000, 0.000000, 0.000000)</string>
					<key>Dev</key>
					<real>0.0</real>
					<key>IndexInImage</key>
					<integer>14</integer>
					<key>Max</key>
					<real>0.0</real>
					<key>Mean</key>
					<real>0.0</real>
					<key>Min</key>
					<real>0.0</real>
					<key>Name</key>
					<string>Calcification</string>
					<key>NumberOfPoints</key>
					<integer>1</integer>
					<key>Point_mm</key>
					<array>
						<string>(0.000000, 0.000000, 0.000000)</string>
					</array>
					<key>Point_px</key>
					<array>
						<string>(2437.929932, 1956.160034)</string>
					</array>
					<key>Total</key>
					<real>0.0</real>
					<key>Type</key>
					<integer>19</integer>
				</dict>
				<dict>
					<key>Area</key>
					<real>0.0</real>
					<key>Center</key>
					<string>(0.000000, 0.000000, 0.000000)</string>
					<key>Dev</key>
					<real>0.0</real>
					<key>IndexInImage</key>
					<integer>15</integer>
					<key>Max</key>
					<real>0.0</real>
					<key>Mean</key>
					<real>0.0</real>
					<key>Min</key>
					<real>0.0</real>
					<key>Name</key>
					<string>Calcification</string>
					<key>NumberOfPoints</key>
					<integer>1</integer>
					<key>Point_mm</key>
					<array>
						<string>(0.000000, 0.000000, 0.000000)</string>
					</array>
					<key>Point_px</key>
					<array>
						<string>(1436.219971, 1997.219971)</string>
					</array>
					<key>Total</key>
					<real>0.0</real>
					<key>Type</key>
					<integer>19</integer>
				</dict>
				<dict>
					<key>Area</key>
					<real>0.0</real>
					<key>Center</key>
					<string>(0.000000, 0.000000, 0.000000)</string>
					<key>Dev</key>
					<real>0.0</real>
					<key>IndexInImage</key>
					<integer>16</integer>
					<key>Max</key>
					<real>0.0</real>
					<key>Mean</key>
					<real>0.0</real>
					<key>Min</key>
					<real>0.0</real>
					<key>Name</key>
					<string>Calcification</string>
					<key>NumberOfPoints</key>
					<integer>1</integer>
					<key>Point_mm</key>
					<array>
						<string>(0.000000, 0.000000, 0.000000)</string>
					</array>
					<key>Point_px</key>
					<array>
						<string>(1431.739990, 1958.079956)</string>
					</array>
					<key>Total</key>
					<real>0.0</real>
					<key>Type</key>
					<integer>19</integer>
				</dict>
				<dict>
					<key>Area</key>
					<real>0.0</real>
					<key>Center</key>
					<string>(0.000000, 0.000000, 0.000000)</string>
					<key>Dev</key>
					<real>0.0</real>
					<key>IndexInImage</key>
					<integer>17</integer>
					<key>Max</key>
					<real>0.0</real>
					<key>Mean</key>
					<real>0.0</real>
					<key>Min</key>
					<real>0.0</real>
					<key>Name</key>
					<string>Calcification</string>
					<key>NumberOfPoints</key>
					<integer>1</integer>
					<key>Point_mm</key>
					<array>
						<string>(0.000000, 0.000000, 0.000000)</string>
					</array>
					<key>Point_px</key>
					<array>
						<string>(1791.780029, 1652.849976)</string>
					</array>
					<key>Total</key>
					<real>0.0</real>
					<key>Type</key>
					<integer>19</integer>
				</dict>
				<dict>
					<key>Area</key>
					<real>0.0</real>
					<key>Center</key>
					<string>(0.000000, 0.000000, 0.000000)</string>
					<key>Dev</key>
					<real>0.0</real>
					<key>IndexInImage</key>
					<integer>18</integer>
					<key>Max</key>
					<real>0.0</real>
					<key>Mean</key>
					<real>0.0</real>
					<key>Min</key>
					<real>0.0</real>
					<key>Name</key>
					<string>Calcification</string>
					<key>NumberOfPoints</key>
					<integer>1</integer>
					<key>Point_mm</key>
					<array>
						<string>(0.000000, 0.000000, 0.000000)</string>
					</array>
					<key>Point_px</key>
					<array>
						<string>(1732.609985, 1657.400024)</string>
					</array>
					<key>Total</key>
					<real>0.0</real>
					<key>Type</key>
					<integer>19</integer>
				</dict>
				<dict>
					<key>Area</key>
					<real>0.0</real>
					<key>Center</key>
					<string>(0.000000, 0.000000, 0.000000)</string>
					<key>Dev</key>
					<real>0.0</real>
					<key>IndexInImage</key>
					<integer>19</integer>
					<key>Max</key>
					<real>0.0</real>
					<key>Mean</key>
					<real>0.0</real>
					<key>Min</key>
					<real>0.0</real>
					<key>Name</key>
					<string>Calcification</string>
					<key>NumberOfPoints</key>
					<integer>1</integer>
					<key>Point_mm</key>
					<array>
						<string>(0.000000, 0.000000, 0.000000)</string>
					</array>
					<key>Point_px</key>
					<array>
						<string>(1710.609985, 1652.089966)</string>
					</array>
					<key>Total</key>
					<real>0.0</real>
					<key>Type</key>
					<integer>19</integer>
				</dict>
				<dict>
					<key>Area</key>
					<real>0.0</real>
					<key>Center</key>
					<string>(0.000000, 0.000000, 0.000000)</string>
					<key>Dev</key>
					<real>0.0</real>
					<key>IndexInImage</key>
					<integer>20</integer>
					<key>Max</key>
					<real>0.0</real>
					<key>Mean</key>
					<real>0.0</real>
					<key>Min</key>
					<real>0.0</real>
					<key>Name</key>
					<string>Calcification</string>
					<key>NumberOfPoints</key>
					<integer>1</integer>
					<key>Point_mm</key>
					<array>
						<string>(0.000000, 0.000000, 0.000000)</string>
					</array>
					<key>Point_px</key>
					<array>
						<string>(1734.130005, 1555.000000)</string>
					</array>
					<key>Total</key>
					<real>0.0</real>
					<key>Type</key>
					<integer>19</integer>
				</dict>
				<dict>
					<key>Area</key>
					<real>0.0</real>
					<key>Center</key>
					<string>(0.000000, 0.000000, 0.000000)</string>
					<key>Dev</key>
					<real>0.0</real>
					<key>IndexInImage</key>
					<integer>21</integer>
					<key>Max</key>
					<real>0.0</real>
					<key>Mean</key>
					<real>0.0</real>
					<key>Min</key>
					<real>0.0</real>
					<key>Name</key>
					<string>Calcification</string>
					<key>NumberOfPoints</key>
					<integer>1</integer>
					<key>Point_mm</key>
					<array>
						<string>(0.000000, 0.000000, 0.000000)</string>
					</array>
					<key>Point_px</key>
					<array>
						<string>(1721.989990, 1552.719971)</string>
					</array>
					<key>Total</key>
					<real>0.0</real>
					<key>Type</key>
					<integer>19</integer>
				</dict>
				<dict>
					<key>Area</key>
					<real>0.0</real>
					<key>Center</key>
					<string>(0.000000, 0.000000, 0.000000)</string>
					<key>Dev</key>
					<real>0.0</real>
					<key>IndexInImage</key>
					<integer>22</integer>
					<key>Max</key>
					<real>0.0</real>
					<key>Mean</key>
					<real>0.0</real>
					<key>Min</key>
					<real>0.0</real>
					<key>Name</key>
					<string>Calcification</string>
					<key>NumberOfPoints</key>
					<integer>1</integer>
					<key>Point_mm</key>
					<array>
						<string>(0.000000, 0.000000, 0.000000)</string>
					</array>
					<key>Point_px</key>
					<array>
						<string>(1661.300049, 1553.479980)</string>
					</array>
					<key>Total</key>
					<real>0.0</real>
					<key>Type</key>
					<integer>19</integer>
				</dict>
				<dict>
					<key>Area</key>
					<real>0.0</real>
					<key>Center</key>
					<string>(0.000000, 0.000000, 0.000000)</string>
					<key>Dev</key>
					<real>0.0</real>
					<key>IndexInImage</key>
					<integer>23</integer>
					<key>Max</key>
					<real>0.0</real>
					<key>Mean</key>
					<real>0.0</real>
					<key>Min</key>
					<real>0.0</real>
					<key>Name</key>
					<string>Calcification</string>
					<key>NumberOfPoints</key>
					<integer>1</integer>
					<key>Point_mm</key>
					<array>
						<string>(0.000000, 0.000000, 0.000000)</string>
					</array>
					<key>Point_px</key>
					<array>
						<string>(1696.199951, 1500.380005)</string>
					</array>
					<key>Total</key>
					<real>0.0</real>
					<key>Type</key>
					<integer>19</integer>
				</dict>
				<dict>
					<key>Area</key>
					<real>0.0</real>
					<key>Center</key>
					<string>(0.000000, 0.000000, 0.000000)</string>
					<key>Dev</key>
					<real>0.0</real>
					<key>IndexInImage</key>
					<integer>24</integer>
					<key>Max</key>
					<real>0.0</real>
					<key>Mean</key>
					<real>0.0</real>
					<key>Min</key>
					<real>0.0</real>
					<key>Name</key>
					<string>Calcification</string>
					<key>NumberOfPoints</key>
					<integer>1</integer>
					<key>Point_mm</key>
					<array>
						<string>(0.000000, 0.000000, 0.000000)</string>
					</array>
					<key>Point_px</key>
					<array>
						<string>(1627.170044, 1561.819946)</string>
					</array>
					<key>Total</key>
					<real>0.0</real>
					<key>Type</key>
					<integer>19</integer>
				</dict>
				<dict>
					<key>Area</key>
					<real>0.0</real>
					<key>Center</key>
					<string>(0.000000, 0.000000, 0.000000)</string>
					<key>Dev</key>
					<real>0.0</real>
					<key>IndexInImage</key>
					<integer>25</integer>
					<key>Max</key>
					<real>0.0</real>
					<key>Mean</key>
					<real>0.0</real>
					<key>Min</key>
					<real>0.0</real>
					<key>Name</key>
					<string>Calcification</string>
					<key>NumberOfPoints</key>
					<integer>1</integer>
					<key>Point_mm</key>
					<array>
						<string>(0.000000, 0.000000, 0.000000)</string>
					</array>
					<key>Point_px</key>
					<array>
						<string>(1930.359985, 1206.900024)</string>
					</array>
					<key>Total</key>
					<real>0.0</real>
					<key>Type</key>
					<integer>19</integer>
				</dict>
				<dict>
					<key>Area</key>
					<real>0.0</real>
					<key>Center</key>
					<string>(0.000000, 0.000000, 0.000000)</string>
					<key>Dev</key>
					<real>0.0</real>
					<key>IndexInImage</key>
					<integer>26</integer>
					<key>Max</key>
					<real>0.0</real>
					<key>Mean</key>
					<real>0.0</real>
					<key>Min</key>
					<real>0.0</real>
					<key>Name</key>
					<string>Calcification</string>
					<key>NumberOfPoints</key>
					<integer>1</integer>
					<key>Point_mm</key>
					<array>
						<string>(0.000000, 0.000000, 0.000000)</string>
					</array>
					<key>Point_px</key>
					<array>
						<string>(2042.949951, 1342.410034)</string>
					</array>
					<key>Total</key>
					<real>0.0</real>
					<key>Type</key>
					<integer>19</integer>
				</dict>
				<dict>
					<key>Area</key>
					<real>0.0</real>
					<key>Center</key>
					<string>(0.000000, 0.000000, 0.000000)</string>
					<key>Dev</key>
					<real>0.0</real>
					<key>IndexInImage</key>
					<integer>27</integer>
					<key>Max</key>
					<real>0.0</real>
					<key>Mean</key>
					<real>0.0</real>
					<key>Min</key>
					<real>0.0</real>
					<key>Name</key>
					<string>Calcification</string>
					<key>NumberOfPoints</key>
					<integer>1</integer>
					<key>Point_mm</key>
					<array>
						<string>(0.000000, 0.000000, 0.000000)</string>
					</array>
					<key>Point_px</key>
					<array>
						<string>(2206.100098, 1311.400024)</string>
					</array>
					<key>Total</key>
					<real>0.0</real>
					<key>Type</key>
					<integer>19</integer>
				</dict>
				<dict>
					<key>Area</key>
					<real>0.0</real>
					<key>Center</key>
					<string>(0.000000, 0.000000, 0.000000)</string>
					<key>Dev</key>
					<real>0.0</real>
					<key>IndexInImage</key>
					<integer>28</integer>
					<key>Max</key>
					<real>0.0</real>
					<key>Mean</key>
					<real>0.0</real>
					<key>Min</key>
					<real>0.0</real>
					<key>Name</key>
					<string>Calcification</string>
					<key>NumberOfPoints</key>
					<integer>1</integer>
					<key>Point_mm</key>
					<array>
						<string>(0.000000, 0.000000, 0.000000)</string>
					</array>
					<key>Point_px</key>
					<array>
						<string>(2071.939941, 1295.890015)</string>
					</array>
					<key>Total</key>
					<real>0.0</real>
					<key>Type</key>
					<integer>19</integer>
				</dict>
				<dict>
					<key>Area</key>
					<real>0.0</real>
					<key>Center</key>
					<string>(0.000000, 0.000000, 0.000000)</string>
					<key>Dev</key>
					<real>0.0</real>
					<key>IndexInImage</key>
					<integer>29</integer>
					<key>Max</key>
					<real>0.0</real>
					<key>Mean</key>
					<real>0.0</real>
					<key>Min</key>
					<real>0.0</real>
					<key>Name</key>
					<string>Calcification</string>
					<key>NumberOfPoints</key>
					<integer>1</integer>
					<key>Point_mm</key>
					<array>
						<string>(0.000000, 0.000000, 0.000000)</string>
					</array>
					<key>Point_px</key>
					<array>
						<string>(2040.250000, 1226.449951)</string>
					</array>
					<key>Total</key>
					<real>0.0</real>
					<key>Type</key>
					<integer>19</integer>
				</dict>
				<dict>
					<key>Area</key>
					<real>0.0</real>
					<key>Center</key>
					<string>(0.000000, 0.000000, 0.000000)</string>
					<key>Dev</key>
					<real>0.0</real>
					<key>IndexInImage</key>
					<integer>30</integer>
					<key>Max</key>
					<real>0.0</real>
					<key>Mean</key>
					<real>0.0</real>
					<key>Min</key>
					<real>0.0</real>
					<key>Name</key>
					<string>Calcification</string>
					<key>NumberOfPoints</key>
					<integer>1</integer>
					<key>Point_mm</key>
					<array>
						<string>(0.000000, 0.000000, 0.000000)</string>
					</array>
					<key>Point_px</key>
					<array>
						<string>(2020.699951, 1226.449951)</string>
					</array>
					<key>Total</key>
					<real>0.0</real>
					<key>Type</key>
					<integer>19</integer>
				</dict>
				<dict>
					<key>Area</key>
					<real>0.0</real>
					<key>Center</key>
					<string>(0.000000, 0.000000, 0.000000)</string>
					<key>Dev</key>
					<real>0.0</real>
					<key>IndexInImage</key>
					<integer>31</integer>
					<key>Max</key>
					<real>0.0</real>
					<key>Mean</key>
					<real>0.0</real>
					<key>Min</key>
					<real>0.0</real>
					<key>Name</key>
					<string>Calcification</string>
					<key>NumberOfPoints</key>
					<integer>1</integer>
					<key>Point_mm</key>
					<array>
						<string>(0.000000, 0.000000, 0.000000)</string>
					</array>
					<key>Point_px</key>
					<array>
						<string>(2018.000000, 1188.689941)</string>
					</array>
					<key>Total</key>
					<real>0.0</real>
					<key>Type</key>
					<integer>19</integer>
				</dict>
				<dict>
					<key>Area</key>
					<real>0.0</real>
					<key>Center</key>
					<string>(0.000000, 0.000000, 0.000000)</string>
					<key>Dev</key>
					<real>0.0</real>
					<key>IndexInImage</key>
					<integer>32</integer>
					<key>Max</key>
					<real>0.0</real>
					<key>Mean</key>
					<real>0.0</real>
					<key>Min</key>
					<real>0.0</real>
					<key>Name</key>
					<string>Calcification</string>
					<key>NumberOfPoints</key>
					<integer>1</integer>
					<key>Point_mm</key>
					<array>
						<string>(0.000000, 0.000000, 0.000000)</string>
					</array>
					<key>Point_px</key>
					<array>
						<string>(2028.790039, 1166.449951)</string>
					</array>
					<key>Total</key>
					<real>0.0</real>
					<key>Type</key>
					<integer>19</integer>
				</dict>
				<dict>
					<key>Area</key>
					<real>0.0</real>
					<key>Center</key>
					<string>(0.000000, 0.000000, 0.000000)</string>
					<key>Dev</key>
					<real>0.0</real>
					<key>IndexInImage</key>
					<integer>33</integer>
					<key>Max</key>
					<real>0.0</real>
					<key>Mean</key>
					<real>0.0</real>
					<key>Min</key>
					<real>0.0</real>
					<key>Name</key>
					<string>Calcification</string>
					<key>NumberOfPoints</key>
					<integer>1</integer>
					<key>Point_mm</key>
					<array>
						<string>(0.000000, 0.000000, 0.000000)</string>
					</array>
					<key>Point_px</key>
					<array>
						<string>(2084.070068, 1074.760010)</string>
					</array>
					<key>Total</key>
					<real>0.0</real>
					<key>Type</key>
					<integer>19</integer>
				</dict>
				<dict>
					<key>Area</key>
					<real>0.0</real>
					<key>Center</key>
					<string>(0.000000, 0.000000, 0.000000)</string>
					<key>Dev</key>
					<real>0.0</real>
					<key>IndexInImage</key>
					<integer>34</integer>
					<key>Max</key>
					<real>0.0</real>
					<key>Mean</key>
					<real>0.0</real>
					<key>Min</key>
					<real>0.0</real>
					<key>Name</key>
					<string>Calcification</string>
					<key>NumberOfPoints</key>
					<integer>1</integer>
					<key>Point_mm</key>
					<array>
						<string>(0.000000, 0.000000, 0.000000)</string>
					</array>
					<key>Point_px</key>
					<array>
						<string>(2142.050049, 1040.369995)</string>
					</array>
					<key>Total</key>
					<real>0.0</real>
					<key>Type</key>
					<integer>19</integer>
				</dict>
				<dict>
					<key>Area</key>
					<real>0.0</real>
					<key>Center</key>
					<string>(0.000000, 0.000000, 0.000000)</string>
					<key>Dev</key>
					<real>0.0</real>
					<key>IndexInImage</key>
					<integer>35</integer>
					<key>Max</key>
					<real>0.0</real>
					<key>Mean</key>
					<real>0.0</real>
					<key>Min</key>
					<real>0.0</real>
					<key>Name</key>
					<string>Calcification</string>
					<key>NumberOfPoints</key>
					<integer>1</integer>
					<key>Point_mm</key>
					<array>
						<string>(0.000000, 0.000000, 0.000000)</string>
					</array>
					<key>Point_px</key>
					<array>
						<string>(2043.619995, 1074.760010)</string>
					</array>
					<key>Total</key>
					<real>0.0</real>
					<key>Type</key>
					<integer>19</integer>
				</dict>
				<dict>
					<key>Area</key>
					<real>0.0</real>
					<key>Center</key>
					<string>(0.000000, 0.000000, 0.000000)</string>
					<key>Dev</key>
					<real>0.0</real>
					<key>IndexInImage</key>
					<integer>36</integer>
					<key>Max</key>
					<real>0.0</real>
					<key>Mean</key>
					<real>0.0</real>
					<key>Min</key>
					<real>0.0</real>
					<key>Name</key>
					<string>Calcification</string>
					<key>NumberOfPoints</key>
					<integer>1</integer>
					<key>Point_mm</key>
					<array>
						<string>(0.000000, 0.000000, 0.000000)</string>
					</array>
					<key>Point_px</key>
					<array>
						<string>(2066.540039, 1037.000000)</string>
					</array>
					<key>Total</key>
					<real>0.0</real>
					<key>Type</key>
					<integer>19</integer>
				</dict>
				<dict>
					<key>Area</key>
					<real>0.0</real>
					<key>Center</key>
					<string>(0.000000, 0.000000, 0.000000)</string>
					<key>Dev</key>
					<real>0.0</real>
					<key>IndexInImage</key>
					<integer>37</integer>
					<key>Max</key>
					<real>0.0</real>
					<key>Mean</key>
					<real>0.0</real>
					<key>Min</key>
					<real>0.0</real>
					<key>Name</key>
					<string>Calcification</string>
					<key>NumberOfPoints</key>
					<integer>1</integer>
					<key>Point_mm</key>
					<array>
						<string>(0.000000, 0.000000, 0.000000)</string>
					</array>
					<key>Point_px</key>
					<array>
						<string>(2069.909912, 993.179016)</string>
					</array>
					<key>Total</key>
					<real>0.0</real>
					<key>Type</key>
					<integer>19</integer>
				</dict>
				<dict>
					<key>Area</key>
					<real>0.0</real>
					<key>Center</key>
					<string>(0.000000, 0.000000, 0.000000)</string>
					<key>Dev</key>
					<real>0.0</real>
					<key>IndexInImage</key>
					<integer>38</integer>
					<key>Max</key>
					<real>0.0</real>
					<key>Mean</key>
					<real>0.0</real>
					<key>Min</key>
					<real>0.0</real>
					<key>Name</key>
					<string>Calcification</string>
					<key>NumberOfPoints</key>
					<integer>1</integer>
					<key>Point_mm</key>
					<array>
						<string>(0.000000, 0.000000, 0.000000)</string>
					</array>
					<key>Point_px</key>
					<array>
						<string>(2063.169922, 995.875977)</string>
					</array>
					<key>Total</key>
					<real>0.0</real>
					<key>Type</key>
					<integer>19</integer>
				</dict>
				<dict>
					<key>Area</key>
					<real>0.0</real>
					<key>Center</key>
					<string>(0.000000, 0.000000, 0.000000)</string>
					<key>Dev</key>
					<real>0.0</real>
					<key>IndexInImage</key>
					<integer>39</integer>
					<key>Max</key>
					<real>0.0</real>
					<key>Mean</key>
					<real>0.0</real>
					<key>Min</key>
					<real>0.0</real>
					<key>Name</key>
					<string>Calcification</string>
					<key>NumberOfPoints</key>
					<integer>1</integer>
					<key>Point_mm</key>
					<array>
						<string>(0.000000, 0.000000, 0.000000)</string>
					</array>
					<key>Point_px</key>
					<array>
						<string>(2104.300049, 979.695984)</string>
					</array>
					<key>Total</key>
					<real>0.0</real>
					<key>Type</key>
					<integer>19</integer>
				</dict>
				<dict>
					<key>Area</key>
					<real>0.0</real>
					<key>Center</key>
					<string>(0.000000, 0.000000, 0.000000)</string>
					<key>Dev</key>
					<real>0.0</real>
					<key>IndexInImage</key>
					<integer>40</integer>
					<key>Max</key>
					<real>0.0</real>
					<key>Mean</key>
					<real>0.0</real>
					<key>Min</key>
					<real>0.0</real>
					<key>Name</key>
					<string>Calcification</string>
					<key>NumberOfPoints</key>
					<integer>1</integer>
					<key>Point_mm</key>
					<array>
						<string>(0.000000, 0.000000, 0.000000)</string>
					</array>
					<key>Point_px</key>
					<array>
						<string>(2082.050049, 975.651001)</string>
					</array>
					<key>Total</key>
					<real>0.0</real>
					<key>Type</key>
					<integer>19</integer>
				</dict>
				<dict>
					<key>Area</key>
					<real>0.0</real>
					<key>Center</key>
					<string>(0.000000, 0.000000, 0.000000)</string>
					<key>Dev</key>
					<real>0.0</real>
					<key>IndexInImage</key>
					<integer>41</integer>
					<key>Max</key>
					<real>0.0</real>
					<key>Mean</key>
					<real>0.0</real>
					<key>Min</key>
					<real>0.0</real>
					<key>Name</key>
					<string>Calcification</string>
					<key>NumberOfPoints</key>
					<integer>1</integer>
					<key>Point_mm</key>
					<array>
						<string>(0.000000, 0.000000, 0.000000)</string>
					</array>
					<key>Point_px</key>
					<array>
						<string>(2068.560059, 983.067017)</string>
					</array>
					<key>Total</key>
					<real>0.0</real>
					<key>Type</key>
					<integer>19</integer>
				</dict>
				<dict>
					<key>Area</key>
					<real>0.0</real>
					<key>Center</key>
					<string>(0.000000, 0.000000, 0.000000)</string>
					<key>Dev</key>
					<real>0.0</real>
					<key>IndexInImage</key>
					<integer>42</integer>
					<key>Max</key>
					<real>0.0</real>
					<key>Mean</key>
					<real>0.0</real>
					<key>Min</key>
					<real>0.0</real>
					<key>Name</key>
					<string>Calcification</string>
					<key>NumberOfPoints</key>
					<integer>1</integer>
					<key>Point_mm</key>
					<array>
						<string>(0.000000, 0.000000, 0.000000)</string>
					</array>
					<key>Point_px</key>
					<array>
						<string>(2061.580078, 842.716003)</string>
					</array>
					<key>Total</key>
					<real>0.0</real>
					<key>Type</key>
					<integer>19</integer>
				</dict>
				<dict>
					<key>Area</key>
					<real>0.0</real>
					<key>Center</key>
					<string>(0.000000, 0.000000, 0.000000)</string>
					<key>Dev</key>
					<real>0.0</real>
					<key>IndexInImage</key>
					<integer>43</integer>
					<key>Max</key>
					<real>0.0</real>
					<key>Mean</key>
					<real>0.0</real>
					<key>Min</key>
					<real>0.0</real>
					<key>Name</key>
					<string>Calcification</string>
					<key>NumberOfPoints</key>
					<integer>1</integer>
					<key>Point_mm</key>
					<array>
						<string>(0.000000, 0.000000, 0.000000)</string>
					</array>
					<key>Point_px</key>
					<array>
						<string>(2232.340088, 887.302002)</string>
					</array>
					<key>Total</key>
					<real>0.0</real>
					<key>Type</key>
					<integer>19</integer>
				</dict>
				<dict>
					<key>Area</key>
					<real>0.0</real>
					<key>Center</key>
					<string>(0.000000, 0.000000, 0.000000)</string>
					<key>Dev</key>
					<real>0.0</real>
					<key>IndexInImage</key>
					<integer>44</integer>
					<key>Max</key>
					<real>0.0</real>
					<key>Mean</key>
					<real>0.0</real>
					<key>Min</key>
					<real>0.0</real>
					<key>Name</key>
					<string>Calcification</string>
					<key>NumberOfPoints</key>
					<integer>1</integer>
					<key>Point_mm</key>
					<array>
						<string>(0.000000, 0.000000, 0.000000)</string>
					</array>
					<key>Point_px</key>
					<array>
						<string>(2213.840088, 883.507996)</string>
					</array>
					<key>Total</key>
					<real>0.0</real>
					<key>Type</key>
					<integer>19</integer>
				</dict>
				<dict>
					<key>Area</key>
					<real>0.0</real>
					<key>Center</key>
					<string>(0.000000, 0.000000, 0.000000)</string>
					<key>Dev</key>
					<real>0.0</real>
					<key>IndexInImage</key>
					<integer>45</integer>
					<key>Max</key>
					<real>0.0</real>
					<key>Mean</key>
					<real>0.0</real>
					<key>Min</key>
					<real>0.0</real>
					<key>Name</key>
					<string>Calcification</string>
					<key>NumberOfPoints</key>
					<integer>1</integer>
					<key>Point_mm</key>
					<array>
						<string>(0.000000, 0.000000, 0.000000)</string>
					</array>
					<key>Point_px</key>
					<array>
						<string>(2284.989990, 837.023987)</string>
					</array>
					<key>Total</key>
					<real>0.0</real>
					<key>Type</key>
					<integer>19</integer>
				</dict>
				<dict>
					<key>Area</key>
					<real>0.0</real>
					<key>Center</key>
					<string>(0.000000, 0.000000, 0.000000)</string>
					<key>Dev</key>
					<real>0.0</real>
					<key>IndexInImage</key>
					<integer>46</integer>
					<key>Max</key>
					<real>0.0</real>
					<key>Mean</key>
					<real>0.0</real>
					<key>Min</key>
					<real>0.0</real>
					<key>Name</key>
					<string>Calcification</string>
					<key>NumberOfPoints</key>
					<integer>1</integer>
					<key>Point_mm</key>
					<array>
						<string>(0.000000, 0.000000, 0.000000)</string>
					</array>
					<key>Point_px</key>
					<array>
						<string>(1394.839966, 1577.819946)</string>
					</array>
					<key>Total</key>
					<real>0.0</real>
					<key>Type</key>
					<integer>19</integer>
				</dict>
				<dict>
					<key>Area</key>
					<real>0.0</real>
					<key>Center</key>
					<string>(0.000000, 0.000000, 0.000000)</string>
					<key>Dev</key>
					<real>0.0</real>
					<key>IndexInImage</key>
					<integer>47</integer>
					<key>Max</key>
					<real>0.0</real>
					<key>Mean</key>
					<real>0.0</real>
					<key>Min</key>
					<real>0.0</real>
					<key>Name</key>
					<string>Calcification</string>
					<key>NumberOfPoints</key>
					<integer>1</integer>
					<key>Point_mm</key>
					<array>
						<string>(0.000000, 0.000000, 0.000000)</string>
					</array>
					<key>Point_px</key>
					<array>
						<string>(1480.390015, 1387.130005)</string>
					</array>
					<key>Total</key>
					<real>0.0</real>
					<key>Type</key>
					<integer>19</integer>
				</dict>
				<dict>
					<key>Area</key>
					<real>0.0</real>
					<key>Center</key>
					<string>(0.000000, 0.000000, 0.000000)</string>
					<key>Dev</key>
					<real>0.0</real>
					<key>IndexInImage</key>
					<integer>48</integer>
					<key>Max</key>
					<real>0.0</real>
					<key>Mean</key>
					<real>0.0</real>
					<key>Min</key>
					<real>0.0</real>
					<key>Name</key>
					<string>Calcification</string>
					<key>NumberOfPoints</key>
					<integer>1</integer>
					<key>Point_mm</key>
					<array>
						<string>(0.000000, 0.000000, 0.000000)</string>
					</array>
					<key>Point_px</key>
					<array>
						<string>(1654.859985, 1473.250000)</string>
					</array>
					<key>Total</key>
					<real>0.0</real>
					<key>Type</key>
					<integer>19</integer>
				</dict>
				<dict>
					<key>Area</key>
					<real>0.0</real>
					<key>Center</key>
					<string>(0.000000, 0.000000, 0.000000)</string>
					<key>Dev</key>
					<real>0.0</real>
					<key>IndexInImage</key>
					<integer>49</integer>
					<key>Max</key>
					<real>0.0</real>
					<key>Mean</key>
					<real>0.0</real>
					<key>Min</key>
					<real>0.0</real>
					<key>Name</key>
					<string>Calcification</string>
					<key>NumberOfPoints</key>
					<integer>1</integer>
					<key>Point_mm</key>
					<array>
						<string>(0.000000, 0.000000, 0.000000)</string>
					</array>
					<key>Point_px</key>
					<array>
						<string>(1657.099976, 1456.469971)</string>
					</array>
					<key>Total</key>
					<real>0.0</real>
					<key>Type</key>
					<integer>19</integer>
				</dict>
				<dict>
					<key>Area</key>
					<real>0.0</real>
					<key>Center</key>
					<string>(0.000000, 0.000000, 0.000000)</string>
					<key>Dev</key>
					<real>0.0</real>
					<key>IndexInImage</key>
					<integer>50</integer>
					<key>Max</key>
					<real>0.0</real>
					<key>Mean</key>
					<real>0.0</real>
					<key>Min</key>
					<real>0.0</real>
					<key>Name</key>
					<string>Calcification</string>
					<key>NumberOfPoints</key>
					<integer>1</integer>
					<key>Point_mm</key>
					<array>
						<string>(0.000000, 0.000000, 0.000000)</string>
					</array>
					<key>Point_px</key>
					<array>
						<string>(1663.250000, 1440.260010)</string>
					</array>
					<key>Total</key>
					<real>0.0</real>
					<key>Type</key>
					<integer>19</integer>
				</dict>
				<dict>
					<key>Area</key>
					<real>0.0</real>
					<key>Center</key>
					<string>(0.000000, 0.000000, 0.000000)</string>
					<key>Dev</key>
					<real>0.0</real>
					<key>IndexInImage</key>
					<integer>51</integer>
					<key>Max</key>
					<real>0.0</real>
					<key>Mean</key>
					<real>0.0</real>
					<key>Min</key>
					<real>0.0</real>
					<key>Name</key>
					<string>Calcification</string>
					<key>NumberOfPoints</key>
					<integer>1</integer>
					<key>Point_mm</key>
					<array>
						<string>(0.000000, 0.000000, 0.000000)</string>
					</array>
					<key>Point_px</key>
					<array>
						<string>(1489.790039, 1517.910034)</string>
					</array>
					<key>Total</key>
					<real>0.0</real>
					<key>Type</key>
					<integer>19</integer>
				</dict>
				<dict>
					<key>Area</key>
					<real>0.0</real>
					<key>Center</key>
					<string>(0.000000, 0.000000, 0.000000)</string>
					<key>Dev</key>
					<real>0.0</real>
					<key>IndexInImage</key>
					<integer>52</integer>
					<key>Max</key>
					<real>0.0</real>
					<key>Mean</key>
					<real>0.0</real>
					<key>Min</key>
					<real>0.0</real>
					<key>Name</key>
					<string>Calcification</string>
					<key>NumberOfPoints</key>
					<integer>1</integer>
					<key>Point_mm</key>
					<array>
						<string>(0.000000, 0.000000, 0.000000)</string>
					</array>
					<key>Point_px</key>
					<array>
						<string>(1495.770020, 1474.390015)</string>
					</array>
					<key>Total</key>
					<real>0.0</real>
					<key>Type</key>
					<integer>19</integer>
				</dict>
				<dict>
					<key>Area</key>
					<real>0.0</real>
					<key>Center</key>
					<string>(0.000000, 0.000000, 0.000000)</string>
					<key>Dev</key>
					<real>0.0</real>
					<key>IndexInImage</key>
					<integer>53</integer>
					<key>Max</key>
					<real>0.0</real>
					<key>Mean</key>
					<real>0.0</real>
					<key>Min</key>
					<real>0.0</real>
					<key>Name</key>
					<string>Calcification</string>
					<key>NumberOfPoints</key>
					<integer>1</integer>
					<key>Point_mm</key>
					<array>
						<string>(0.000000, 0.000000, 0.000000)</string>
					</array>
					<key>Point_px</key>
					<array>
						<string>(1847.729980, 1448.819946)</string>
					</array>
					<key>Total</key>
					<real>0.0</real>
					<key>Type</key>
					<integer>19</integer>
				</dict>
				<dict>
					<key>Area</key>
					<real>0.0</real>
					<key>Center</key>
					<string>(0.000000, 0.000000, 0.000000)</string>
					<key>Dev</key>
					<real>0.0</real>
					<key>IndexInImage</key>
					<integer>54</integer>
					<key>Max</key>
					<real>0.0</real>
					<key>Mean</key>
					<real>0.0</real>
					<key>Min</key>
					<real>0.0</real>
					<key>Name</key>
					<string>Calcification</string>
					<key>NumberOfPoints</key>
					<integer>1</integer>
					<key>Point_mm</key>
					<array>
						<string>(0.000000, 0.000000, 0.000000)</string>
					</array>
					<key>Point_px</key>
					<array>
						<string>(1964.689941, 1439.569946)</string>
					</array>
					<key>Total</key>
					<real>0.0</real>
					<key>Type</key>
					<integer>19</integer>
				</dict>
				<dict>
					<key>Area</key>
					<real>0.0</real>
					<key>Center</key>
					<string>(0.000000, 0.000000, 0.000000)</string>
					<key>Dev</key>
					<real>0.0</real>
					<key>IndexInImage</key>
					<integer>55</integer>
					<key>Max</key>
					<real>0.0</real>
					<key>Mean</key>
					<real>0.0</real>
					<key>Min</key>
					<real>0.0</real>
					<key>Name</key>
					<string>Calcification</string>
					<key>NumberOfPoints</key>
					<integer>1</integer>
					<key>Point_mm</key>
					<array>
						<string>(0.000000, 0.000000, 0.000000)</string>
					</array>
					<key>Point_px</key>
					<array>
						<string>(2037.579956, 1528.780029)</string>
					</array>
					<key>Total</key>
					<real>0.0</real>
					<key>Type</key>
					<integer>19</integer>
				</dict>
				<dict>
					<key>Area</key>
					<real>0.0</real>
					<key>Center</key>
					<string>(0.000000, 0.000000, 0.000000)</string>
					<key>Dev</key>
					<real>0.0</real>
					<key>IndexInImage</key>
					<integer>56</integer>
					<key>Max</key>
					<real>0.0</real>
					<key>Mean</key>
					<real>0.0</real>
					<key>Min</key>
					<real>0.0</real>
					<key>Name</key>
					<string>Calcification</string>
					<key>NumberOfPoints</key>
					<integer>1</integer>
					<key>Point_mm</key>
					<array>
						<string>(0.000000, 0.000000, 0.000000)</string>
					</array>
					<key>Point_px</key>
					<array>
						<string>(1924.430054, 1446.640015)</string>
					</array>
					<key>Total</key>
					<real>0.0</real>
					<key>Type</key>
					<integer>19</integer>
				</dict>
				<dict>
					<key>Area</key>
					<real>0.0</real>
					<key>Center</key>
					<string>(0.000000, 0.000000, 0.000000)</string>
					<key>Dev</key>
					<real>0.0</real>
					<key>IndexInImage</key>
					<integer>57</integer>
					<key>Max</key>
					<real>0.0</real>
					<key>Mean</key>
					<real>0.0</real>
					<key>Min</key>
					<real>0.0</real>
					<key>Name</key>
					<string>Calcification</string>
					<key>NumberOfPoints</key>
					<integer>1</integer>
					<key>Point_mm</key>
					<array>
						<string>(0.000000, 0.000000, 0.000000)</string>
					</array>
					<key>Point_px</key>
					<array>
						<string>(1786.569946, 1500.609985)</string>
					</array>
					<key>Total</key>
					<real>0.0</real>
					<key>Type</key>
					<integer>19</integer>
				</dict>
				<dict>
					<key>Area</key>
					<real>0.0</real>
					<key>Center</key>
					<string>(0.000000, 0.000000, 0.000000)</string>
					<key>Dev</key>
					<real>0.0</real>
					<key>IndexInImage</key>
					<integer>58</integer>
					<key>Max</key>
					<real>0.0</real>
					<key>Mean</key>
					<real>0.0</real>
					<key>Min</key>
					<real>0.0</real>
					<key>Name</key>
					<string>Calcification</string>
					<key>NumberOfPoints</key>
					<integer>1</integer>
					<key>Point_mm</key>
					<array>
						<string>(0.000000, 0.000000, 0.000000)</string>
					</array>
					<key>Point_px</key>
					<array>
						<string>(1815.810059, 1500.609985)</string>
					</array>
					<key>Total</key>
					<real>0.0</real>
					<key>Type</key>
					<integer>19</integer>
				</dict>
				<dict>
					<key>Area</key>
					<real>0.0</real>
					<key>Center</key>
					<string>(0.000000, 0.000000, 0.000000)</string>
					<key>Dev</key>
					<real>0.0</real>
					<key>IndexInImage</key>
					<integer>59</integer>
					<key>Max</key>
					<real>0.0</real>
					<key>Mean</key>
					<real>0.0</real>
					<key>Min</key>
					<real>0.0</real>
					<key>Name</key>
					<string>Calcification</string>
					<key>NumberOfPoints</key>
					<integer>1</integer>
					<key>Point_mm</key>
					<array>
						<string>(0.000000, 0.000000, 0.000000)</string>
					</array>
					<key>Point_px</key>
					<array>
						<string>(2387.909912, 791.489014)</string>
					</array>
					<key>Total</key>
					<real>0.0</real>
					<key>Type</key>
					<integer>19</integer>
				</dict>
				<dict>
					<key>Area</key>
					<real>0.0</real>
					<key>Center</key>
					<string>(0.000000, 0.000000, 0.000000)</string>
					<key>Dev</key>
					<real>0.0</real>
					<key>IndexInImage</key>
					<integer>60</integer>
					<key>Max</key>
					<real>0.0</real>
					<key>Mean</key>
					<real>0.0</real>
					<key>Min</key>
					<real>0.0</real>
					<key>Name</key>
					<string>Calcification</string>
					<key>NumberOfPoints</key>
					<integer>1</integer>
					<key>Point_mm</key>
					<array>
						<string>(0.000000, 0.000000, 0.000000)</string>
					</array>
					<key>Point_px</key>
					<array>
						<string>(2421.590088, 774.888000)</string>
					</array>
					<key>Total</key>
					<real>0.0</real>
					<key>Type</key>
					<integer>19</integer>
				</dict>
				<dict>
					<key>Area</key>
					<real>0.0</real>
					<key>Center</key>
					<string>(0.000000, 0.000000, 0.000000)</string>
					<key>Dev</key>
					<real>0.0</real>
					<key>IndexInImage</key>
					<integer>61</integer>
					<key>Max</key>
					<real>0.0</real>
					<key>Mean</key>
					<real>0.0</real>
					<key>Min</key>
					<real>0.0</real>
					<key>Name</key>
					<string>Calcification</string>
					<key>NumberOfPoints</key>
					<integer>1</integer>
					<key>Point_mm</key>
					<array>
						<string>(0.000000, 0.000000, 0.000000)</string>
					</array>
					<key>Point_px</key>
					<array>
						<string>(2416.850098, 781.528992)</string>
					</array>
					<key>Total</key>
					<real>0.0</real>
					<key>Type</key>
					<integer>19</integer>
				</dict>
				<dict>
					<key>Area</key>
					<real>0.0</real>
					<key>Center</key>
					<string>(0.000000, 0.000000, 0.000000)</string>
					<key>Dev</key>
					<real>0.0</real>
					<key>IndexInImage</key>
					<integer>62</integer>
					<key>Max</key>
					<real>0.0</real>
					<key>Mean</key>
					<real>0.0</real>
					<key>Min</key>
					<real>0.0</real>
					<key>Name</key>
					<string>Calcification</string>
					<key>NumberOfPoints</key>
					<integer>1</integer>
					<key>Point_mm</key>
					<array>
						<string>(0.000000, 0.000000, 0.000000)</string>
					</array>
					<key>Point_px</key>
					<array>
						<string>(2111.389893, 1830.170044)</string>
					</array>
					<key>Total</key>
					<real>0.0</real>
					<key>Type</key>
					<integer>19</integer>
				</dict>
				<dict>
					<key>Area</key>
					<real>0.0</real>
					<key>Center</key>
					<string>(0.000000, 0.000000, 0.000000)</string>
					<key>Dev</key>
					<real>0.0</real>
					<key>IndexInImage</key>
					<integer>63</integer>
					<key>Max</key>
					<real>0.0</real>
					<key>Mean</key>
					<real>0.0</real>
					<key>Min</key>
					<real>0.0</real>
					<key>Name</key>
					<string>Calcification</string>
					<key>NumberOfPoints</key>
					<integer>1</integer>
					<key>Point_mm</key>
					<array>
						<string>(0.000000, 0.000000, 0.000000)</string>
					</array>
					<key>Point_px</key>
					<array>
						<string>(1868.760010, 1778.109985)</string>
					</array>
					<key>Total</key>
					<real>0.0</real>
					<key>Type</key>
					<integer>19</integer>
				</dict>
				<dict>
					<key>Area</key>
					<real>0.0</real>
					<key>Center</key>
					<string>(0.000000, 0.000000, 0.000000)</string>
					<key>Dev</key>
					<real>0.0</real>
					<key>IndexInImage</key>
					<integer>64</integer>
					<key>Max</key>
					<real>0.0</real>
					<key>Mean</key>
					<real>0.0</real>
					<key>Min</key>
					<real>0.0</real>
					<key>Name</key>
					<string>Calcification</string>
					<key>NumberOfPoints</key>
					<integer>1</integer>
					<key>Point_mm</key>
					<array>
						<string>(0.000000, 0.000000, 0.000000)</string>
					</array>
					<key>Point_px</key>
					<array>
						<string>(1865.229980, 1782.969971)</string>
					</array>
					<key>Total</key>
					<real>0.0</real>
					<key>Type</key>
					<integer>19</integer>
				</dict>
				<dict>
					<key>Area</key>
					<real>0.0</real>
					<key>Center</key>
					<string>(0.000000, 0.000000, 0.000000)</string>
					<key>Dev</key>
					<real>0.0</real>
					<key>IndexInImage</key>
					<integer>65</integer>
					<key>Max</key>
					<real>0.0</real>
					<key>Mean</key>
					<real>0.0</real>
					<key>Min</key>
					<real>0.0</real>
					<key>Name</key>
					<string>Calcification</string>
					<key>NumberOfPoints</key>
					<integer>1</integer>
					<key>Point_mm</key>
					<array>
						<string>(0.000000, 0.000000, 0.000000)</string>
					</array>
					<key>Point_px</key>
					<array>
						<string>(1886.010010, 1799.780029)</string>
					</array>
					<key>Total</key>
					<real>0.0</real>
					<key>Type</key>
					<integer>19</integer>
				</dict>
				<dict>
					<key>Area</key>
					<real>0.0</real>
					<key>Center</key>
					<string>(0.000000, 0.000000, 0.000000)</string>
					<key>Dev</key>
					<real>0.0</real>
					<key>IndexInImage</key>
					<integer>66</integer>
					<key>Max</key>
					<real>0.0</real>
					<key>Mean</key>
					<real>0.0</real>
					<key>Min</key>
					<real>0.0</real>
					<key>Name</key>
					<string>Calcification</string>
					<key>NumberOfPoints</key>
					<integer>1</integer>
					<key>Point_mm</key>
					<array>
						<string>(0.000000, 0.000000, 0.000000)</string>
					</array>
					<key>Point_px</key>
					<array>
						<string>(1737.920044, 1664.989990)</string>
					</array>
					<key>Total</key>
					<real>0.0</real>
					<key>Type</key>
					<integer>19</integer>
				</dict>
				<dict>
					<key>Area</key>
					<real>0.0</real>
					<key>Center</key>
					<string>(0.000000, 0.000000, 0.000000)</string>
					<key>Dev</key>
					<real>0.0</real>
					<key>IndexInImage</key>
					<integer>67</integer>
					<key>Max</key>
					<real>0.0</real>
					<key>Mean</key>
					<real>0.0</real>
					<key>Min</key>
					<real>0.0</real>
					<key>Name</key>
					<string>Calcification</string>
					<key>NumberOfPoints</key>
					<integer>1</integer>
					<key>Point_mm</key>
					<array>
						<string>(0.000000, 0.000000, 0.000000)</string>
					</array>
					<key>Point_px</key>
					<array>
						<string>(1911.630005, 1808.359985)</string>
					</array>
					<key>Total</key>
					<real>0.0</real>
					<key>Type</key>
					<integer>19</integer>
				</dict>
				<dict>
					<key>Area</key>
					<real>0.0</real>
					<key>Center</key>
					<string>(0.000000, 0.000000, 0.000000)</string>
					<key>Dev</key>
					<real>0.0</real>
					<key>IndexInImage</key>
					<integer>68</integer>
					<key>Max</key>
					<real>0.0</real>
					<key>Mean</key>
					<real>0.0</real>
					<key>Min</key>
					<real>0.0</real>
					<key>Name</key>
					<string>Calcification</string>
					<key>NumberOfPoints</key>
					<integer>1</integer>
					<key>Point_mm</key>
					<array>
						<string>(0.000000, 0.000000, 0.000000)</string>
					</array>
					<key>Point_px</key>
					<array>
						<string>(1905.560059, 1735.540039)</string>
					</array>
					<key>Total</key>
					<real>0.0</real>
					<key>Type</key>
					<integer>19</integer>
				</dict>
				<dict>
					<key>Area</key>
					<real>0.0</real>
					<key>Center</key>
					<string>(0.000000, 0.000000, 0.000000)</string>
					<key>Dev</key>
					<real>0.0</real>
					<key>IndexInImage</key>
					<integer>69</integer>
					<key>Max</key>
					<real>0.0</real>
					<key>Mean</key>
					<real>0.0</real>
					<key>Min</key>
					<real>0.0</real>
					<key>Name</key>
					<string>Calcification</string>
					<key>NumberOfPoints</key>
					<integer>1</integer>
					<key>Point_mm</key>
					<array>
						<string>(0.000000, 0.000000, 0.000000)</string>
					</array>
					<key>Point_px</key>
					<array>
						<string>(1901.770020, 1759.810059)</string>
					</array>
					<key>Total</key>
					<real>0.0</real>
					<key>Type</key>
					<integer>19</integer>
				</dict>
				<dict>
					<key>Area</key>
					<real>0.0</real>
					<key>Center</key>
					<string>(0.000000, 0.000000, 0.000000)</string>
					<key>Dev</key>
					<real>0.0</real>
					<key>IndexInImage</key>
					<integer>70</integer>
					<key>Max</key>
					<real>0.0</real>
					<key>Mean</key>
					<real>0.0</real>
					<key>Min</key>
					<real>0.0</real>
					<key>Name</key>
					<string>Calcification</string>
					<key>NumberOfPoints</key>
					<integer>1</integer>
					<key>Point_mm</key>
					<array>
						<string>(0.000000, 0.000000, 0.000000)</string>
					</array>
					<key>Point_px</key>
					<array>
						<string>(1923.010010, 1759.050049)</string>
					</array>
					<key>Total</key>
					<real>0.0</real>
					<key>Type</key>
					<integer>19</integer>
				</dict>
				<dict>
					<key>Area</key>
					<real>0.0</real>
					<key>Center</key>
					<string>(0.000000, 0.000000, 0.000000)</string>
					<key>Dev</key>
					<real>0.0</real>
					<key>IndexInImage</key>
					<integer>71</integer>
					<key>Max</key>
					<real>0.0</real>
					<key>Mean</key>
					<real>0.0</real>
					<key>Min</key>
					<real>0.0</real>
					<key>Name</key>
					<string>Calcification</string>
					<key>NumberOfPoints</key>
					<integer>1</integer>
					<key>Point_mm</key>
					<array>
						<string>(0.000000, 0.000000, 0.000000)</string>
					</array>
					<key>Point_px</key>
					<array>
						<string>(1937.420044, 1767.400024)</string>
					</array>
					<key>Total</key>
					<real>0.0</real>
					<key>Type</key>
					<integer>19</integer>
				</dict>
				<dict>
					<key>Area</key>
					<real>0.0</real>
					<key>Center</key>
					<string>(0.000000, 0.000000, 0.000000)</string>
					<key>Dev</key>
					<real>0.0</real>
					<key>IndexInImage</key>
					<integer>72</integer>
					<key>Max</key>
					<real>0.0</real>
					<key>Mean</key>
					<real>0.0</real>
					<key>Min</key>
					<real>0.0</real>
					<key>Name</key>
					<string>Calcification</string>
					<key>NumberOfPoints</key>
					<integer>1</integer>
					<key>Point_mm</key>
					<array>
						<string>(0.000000, 0.000000, 0.000000)</string>
					</array>
					<key>Point_px</key>
					<array>
						<string>(1897.219971, 1885.729980)</string>
					</array>
					<key>Total</key>
					<real>0.0</real>
					<key>Type</key>
					<integer>19</integer>
				</dict>
				<dict>
					<key>Area</key>
					<real>0.0</real>
					<key>Center</key>
					<string>(0.000000, 0.000000, 0.000000)</string>
					<key>Dev</key>
					<real>0.0</real>
					<key>IndexInImage</key>
					<integer>73</integer>
					<key>Max</key>
					<real>0.0</real>
					<key>Mean</key>
					<real>0.0</real>
					<key>Min</key>
					<real>0.0</real>
					<key>Name</key>
					<string>Calcification</string>
					<key>NumberOfPoints</key>
					<integer>1</integer>
					<key>Point_mm</key>
					<array>
						<string>(0.000000, 0.000000, 0.000000)</string>
					</array>
					<key>Point_px</key>
					<array>
						<string>(1891.150024, 1907.729980)</string>
					</array>
					<key>Total</key>
					<real>0.0</real>
					<key>Type</key>
					<integer>19</integer>
				</dict>
				<dict>
					<key>Area</key>
					<real>0.0</real>
					<key>Center</key>
					<string>(0.000000, 0.000000, 0.000000)</string>
					<key>Dev</key>
					<real>0.0</real>
					<key>IndexInImage</key>
					<integer>74</integer>
					<key>Max</key>
					<real>0.0</real>
					<key>Mean</key>
					<real>0.0</real>
					<key>Min</key>
					<real>0.0</real>
					<key>Name</key>
					<string>Calcification</string>
					<key>NumberOfPoints</key>
					<integer>1</integer>
					<key>Point_mm</key>
					<array>
						<string>(0.000000, 0.000000, 0.000000)</string>
					</array>
					<key>Point_px</key>
					<array>
						<string>(1904.050049, 1897.109985)</string>
					</array>
					<key>Total</key>
					<real>0.0</real>
					<key>Type</key>
					<integer>19</integer>
				</dict>
				<dict>
					<key>Area</key>
					<real>0.0</real>
					<key>Center</key>
					<string>(0.000000, 0.000000, 0.000000)</string>
					<key>Dev</key>
					<real>0.0</real>
					<key>IndexInImage</key>
					<integer>75</integer>
					<key>Max</key>
					<real>0.0</real>
					<key>Mean</key>
					<real>0.0</real>
					<key>Min</key>
					<real>0.0</real>
					<key>Name</key>
					<string>Calcification</string>
					<key>NumberOfPoints</key>
					<integer>1</integer>
					<key>Point_mm</key>
					<array>
						<string>(0.000000, 0.000000, 0.000000)</string>
					</array>
					<key>Point_px</key>
					<array>
						<string>(2023.900024, 1868.290039)</string>
					</array>
					<key>Total</key>
					<real>0.0</real>
					<key>Type</key>
					<integer>19</integer>
				</dict>
				<dict>
					<key>Area</key>
					<real>0.0</real>
					<key>Center</key>
					<string>(0.000000, 0.000000, 0.000000)</string>
					<key>Dev</key>
					<real>0.0</real>
					<key>IndexInImage</key>
					<integer>76</integer>
					<key>Max</key>
					<real>0.0</real>
					<key>Mean</key>
					<real>0.0</real>
					<key>Min</key>
					<real>0.0</real>
					<key>Name</key>
					<string>Calcification</string>
					<key>NumberOfPoints</key>
					<integer>1</integer>
					<key>Point_mm</key>
					<array>
						<string>(0.000000, 0.000000, 0.000000)</string>
					</array>
					<key>Point_px</key>
					<array>
						<string>(1461.270020, 1702.859985)</string>
					</array>
					<key>Total</key>
					<real>0.0</real>
					<key>Type</key>
					<integer>19</integer>
				</dict>
				<dict>
					<key>Area</key>
					<real>0.0</real>
					<key>Center</key>
					<string>(0.000000, 0.000000, 0.000000)</string>
					<key>Dev</key>
					<real>0.0</real>
					<key>IndexInImage</key>
					<integer>77</integer>
					<key>Max</key>
					<real>0.0</real>
					<key>Mean</key>
					<real>0.0</real>
					<key>Min</key>
					<real>0.0</real>
					<key>Name</key>
					<string>Calcification</string>
					<key>NumberOfPoints</key>
					<integer>1</integer>
					<key>Point_mm</key>
					<array>
						<string>(0.000000, 0.000000, 0.000000)</string>
					</array>
					<key>Point_px</key>
					<array>
						<string>(1472.949951, 1680.510010)</string>
					</array>
					<key>Total</key>
					<real>0.0</real>
					<key>Type</key>
					<integer>19</integer>
				</dict>
				<dict>
					<key>Area</key>
					<real>0.0</real>
					<key>Center</key>
					<string>(0.000000, 0.000000, 0.000000)</string>
					<key>Dev</key>
					<real>0.0</real>
					<key>IndexInImage</key>
					<integer>78</integer>
					<key>Max</key>
					<real>0.0</real>
					<key>Mean</key>
					<real>0.0</real>
					<key>Min</key>
					<real>0.0</real>
					<key>Name</key>
					<string>Calcification</string>
					<key>NumberOfPoints</key>
					<integer>1</integer>
					<key>Point_mm</key>
					<array>
						<string>(0.000000, 0.000000, 0.000000)</string>
					</array>
					<key>Point_px</key>
					<array>
						<string>(1489.959961, 1693.520020)</string>
					</array>
					<key>Total</key>
					<real>0.0</real>
					<key>Type</key>
					<integer>19</integer>
				</dict>
				<dict>
					<key>Area</key>
					<real>0.0</real>
					<key>Center</key>
					<string>(0.000000, 0.000000, 0.000000)</string>
					<key>Dev</key>
					<real>0.0</real>
					<key>IndexInImage</key>
					<integer>79</integer>
					<key>Max</key>
					<real>0.0</real>
					<key>Mean</key>
					<real>0.0</real>
					<key>Min</key>
					<real>0.0</real>
					<key>Name</key>
					<string>Calcification</string>
					<key>NumberOfPoints</key>
					<integer>1</integer>
					<key>Point_mm</key>
					<array>
						<string>(0.000000, 0.000000, 0.000000)</string>
					</array>
					<key>Point_px</key>
					<array>
						<string>(1493.959961, 1700.859985)</string>
					</array>
					<key>Total</key>
					<real>0.0</real>
					<key>Type</key>
					<integer>19</integer>
				</dict>
				<dict>
					<key>Area</key>
					<real>0.0</real>
					<key>Center</key>
					<string>(0.000000, 0.000000, 0.000000)</string>
					<key>Dev</key>
					<real>0.0</real>
					<key>IndexInImage</key>
					<integer>80</integer>
					<key>Max</key>
					<real>0.0</real>
					<key>Mean</key>
					<real>0.0</real>
					<key>Min</key>
					<real>0.0</real>
					<key>Name</key>
					<string>Calcification</string>
					<key>NumberOfPoints</key>
					<integer>1</integer>
					<key>Point_mm</key>
					<array>
						<string>(0.000000, 0.000000, 0.000000)</string>
					</array>
					<key>Point_px</key>
					<array>
						<string>(1488.290039, 1712.199951)</string>
					</array>
					<key>Total</key>
					<real>0.0</real>
					<key>Type</key>
					<integer>19</integer>
				</dict>
				<dict>
					<key>Area</key>
					<real>0.0</real>
					<key>Center</key>
					<string>(0.000000, 0.000000, 0.000000)</string>
					<key>Dev</key>
					<real>0.0</real>
					<key>IndexInImage</key>
					<integer>81</integer>
					<key>Max</key>
					<real>0.0</real>
					<key>Mean</key>
					<real>0.0</real>
					<key>Min</key>
					<real>0.0</real>
					<key>Name</key>
					<string>Calcification</string>
					<key>NumberOfPoints</key>
					<integer>1</integer>
					<key>Point_mm</key>
					<array>
						<string>(0.000000, 0.000000, 0.000000)</string>
					</array>
					<key>Point_px</key>
					<array>
						<string>(1506.969971, 1701.859985)</string>
					</array>
					<key>Total</key>
					<real>0.0</real>
					<key>Type</key>
					<integer>19</integer>
				</dict>
				<dict>
					<key>Area</key>
					<real>0.0</real>
					<key>Center</key>
					<string>(0.000000, 0.000000, 0.000000)</string>
					<key>Dev</key>
					<real>0.0</real>
					<key>IndexInImage</key>
					<integer>82</integer>
					<key>Max</key>
					<real>0.0</real>
					<key>Mean</key>
					<real>0.0</real>
					<key>Min</key>
					<real>0.0</real>
					<key>Name</key>
					<string>Calcification</string>
					<key>NumberOfPoints</key>
					<integer>1</integer>
					<key>Point_mm</key>
					<array>
						<string>(0.000000, 0.000000, 0.000000)</string>
					</array>
					<key>Point_px</key>
					<array>
						<string>(1656.510010, 2491.459961)</string>
					</array>
					<key>Total</key>
					<real>0.0</real>
					<key>Type</key>
					<integer>19</integer>
				</dict>
				<dict>
					<key>Area</key>
					<real>0.0</real>
					<key>Center</key>
					<string>(0.000000, 0.000000, 0.000000)</string>
					<key>Dev</key>
					<real>0.0</real>
					<key>IndexInImage</key>
					<integer>83</integer>
					<key>Max</key>
					<real>0.0</real>
					<key>Mean</key>
					<real>0.0</real>
					<key>Min</key>
					<real>0.0</real>
					<key>Name</key>
					<string>Calcification</string>
					<key>NumberOfPoints</key>
					<integer>1</integer>
					<key>Point_mm</key>
					<array>
						<string>(0.000000, 0.000000, 0.000000)</string>
					</array>
					<key>Point_px</key>
					<array>
						<string>(1644.180054, 2524.659912)</string>
					</array>
					<key>Total</key>
					<real>0.0</real>
					<key>Type</key>
					<integer>19</integer>
				</dict>
			</array>
		</dict>
	</array>
</dict>
</plist>
